fast5_rekindler/__init__.py
fast5_rekindler/bam.py
fast5_rekindler/cleanup.py
fast5_rekindler/cli.py
fast5_rekindler/collate.py
fast5_rekindler/index.py
fast5_rekindler/join_dbs.py
fast5_rekindler/logger_config.py
fast5_rekindler/raw_fast5.py
fast5_rekindler-0.0.6.dist-info/METADATA
fast5_rekindler-0.0.6.dist-info/WHEEL
fast5_rekindler-0.0.6.dist-info/entry_points.txt
fast5_rekindler-0.0.6.dist-info/RECORD
