Metadata-Version: 2.1
Name: fast5_rekindler
Version: 0.0.6
Summary: Collates information from BAM and POD5 files and generates FAST5 files for use in legacy tools such as tailfindr.
Home-page: https://adnaniazi.github.io/fast5_rekindler
License: MIT
Author: Adnan M. Niazi
Author-email: adnaniazi@gmail.com
Requires-Python: >=3.10,<3.12
Classifier: Development Status :: 4 - Beta
Classifier: Intended Audience :: Developers
Classifier: License :: OSI Approved :: MIT License
Classifier: Operating System :: OS Independent
Classifier: Programming Language :: Python
Classifier: Programming Language :: Python :: 3
Classifier: Programming Language :: Python :: 3.10
Classifier: Programming Language :: Python :: 3.11
Classifier: Topic :: Software Development :: Libraries :: Python Modules
Classifier: Typing :: Typed
Requires-Dist: click (>=8.1.7,<9.0.0)
Requires-Dist: loguru (>=0.7.2,<0.8.0)
Requires-Dist: mpire (>=2.8.0,<3.0.0)
Requires-Dist: ont-fast5-api (>=4.1.1,<5.0.0)
Requires-Dist: pexpect (>=4.8.0,<5.0.0)
Requires-Dist: pod5 (>=0.2.4,<0.3.0)
Requires-Dist: pysam (>=0.22.0,<0.23.0)
Requires-Dist: types-toml (>=0.10.8.7,<0.11.0.0)
Project-URL: Documentation, https://adnaniazi.github.io/fast5_rekindler
Project-URL: Repository, https://github.com/adnaniazi/fast5_rekindler
